normalize_easy/__init__.py
normalize_easy/normalize_easy.py
normalize_easy-0.0.3.dist-info/DESCRIPTION.rst
normalize_easy-0.0.3.dist-info/METADATA
normalize_easy-0.0.3.dist-info/metadata.json
normalize_easy-0.0.3.dist-info/RECORD
normalize_easy-0.0.3.dist-info/top_level.txt
normalize_easy-0.0.3.dist-info/WHEEL
