Metadata-Version: 2.0
Name: normalize-easy
Version: 0.0.3
Summary: This package implements normc(), normr() and normv() functions to    easily normalize columns and rows of a matrix, and vectors respectively.
Home-page: https://github.com/srambhatla/normalize_easy
Author: Sirisha Rambhatla
Author-email: rambh002@umn.edu
License: BSD
Keywords: normr normc normv normalize rows columns math matrix linear algebra MATLAB
Platform: UNKNOWN
Classifier: Development Status :: 3 - Alpha
Classifier: Topic :: Utilities
Classifier: License :: OSI Approved :: BSD License
Requires-Dist: sklearn
Requires-Dist: numpy
